zuban/__init__.py
zuban-0.0.2.dist-info/METADATA
zuban-0.0.2.dist-info/WHEEL
zuban-0.0.2.dist-info/top_level.txt
zuban-0.0.2.dist-info/RECORD
